.gitlab-ci.yml
.travis.yml
CHANGES.rst
CONTRIBUTORS.rst
DEVELOP.rst
LICENSE.GPL
LICENSE.rst
MANIFEST.in
README.rst
constraints.txt
constraints_plone52.txt
constraints_plone60.txt
requirements.txt
requirements_plone52.txt
requirements_plone60.txt
setup.cfg
setup.py
tox.ini
docs/conf.py
docs/index.rst
src/newsletter/__init__.py
src/newsletter.types.egg-info/PKG-INFO
src/newsletter.types.egg-info/SOURCES.txt
src/newsletter.types.egg-info/dependency_links.txt
src/newsletter.types.egg-info/entry_points.txt
src/newsletter.types.egg-info/namespace_packages.txt
src/newsletter.types.egg-info/not-zip-safe
src/newsletter.types.egg-info/requires.txt
src/newsletter.types.egg-info/top_level.txt
src/newsletter/types/__init__.py
src/newsletter/types/configure.zcml
src/newsletter/types/interfaces.py
src/newsletter/types/permissions.zcml
src/newsletter/types/setuphandlers.py
src/newsletter/types/testing.py
src/newsletter/types/browser/__init__.py
src/newsletter/types/browser/configure.zcml
src/newsletter/types/browser/overrides/.gitkeep
src/newsletter/types/browser/static/.gitkeep
src/newsletter/types/content/__init__.py
src/newsletter/types/content/newsletter.py
src/newsletter/types/content/newsletter.xml
src/newsletter/types/content/newsletter_container.py
src/newsletter/types/content/newsletter_container.xml
src/newsletter/types/locales/README.rst
src/newsletter/types/locales/__init__.py
src/newsletter/types/locales/update.py
src/newsletter/types/locales/update.sh
src/newsletter/types/locales/en/LC_MESSAGES/newsletter.types.po
src/newsletter/types/profiles/default/browserlayer.xml
src/newsletter/types/profiles/default/catalog.xml
src/newsletter/types/profiles/default/metadata.xml
src/newsletter/types/profiles/default/rolemap.xml
src/newsletter/types/profiles/default/types.xml
src/newsletter/types/profiles/default/types.xml.example
src/newsletter/types/profiles/default/registry/main.xml
src/newsletter/types/profiles/default/types/Newsletter.xml
src/newsletter/types/profiles/default/types/NewsletterContainer.xml
src/newsletter/types/profiles/uninstall/browserlayer.xml
src/newsletter/types/restapi/__init__.py
src/newsletter/types/restapi/configure.zcml
src/newsletter/types/restapi/send.py
src/newsletter/types/tests/__init__.py
src/newsletter/types/tests/test_ct_newsletter.py
src/newsletter/types/tests/test_ct_newsletter_container.py
